binauth/__init__.py
binauth/exceptions.py
binauth/fastapi.py
binauth/manager.py
binauth/models.py
binauth/registry.py
binauth/repository.py
binauth/types.py
binauth-0.3.1.dist-info/METADATA
binauth-0.3.1.dist-info/WHEEL
binauth-0.3.1.dist-info/licenses/LICENSE
binauth-0.3.1.dist-info/RECORD
