Metadata-Version: 2.4
Name: binauth
Version: 0.3.1
Summary: Bitwise permission system for Python with SQLAlchemy and FastAPI integration
License: MIT
License-File: LICENSE
Keywords: permissions,authorization,bitwise,fastapi,sqlalchemy
Requires-Python: >=3.12,<4.0
Classifier: Development Status :: 4 - Beta
Classifier: Framework :: FastAPI
Classifier: Intended Audience :: Developers
Classifier: License :: OSI Approved :: MIT License
Classifier: Programming Language :: Python :: 3
Classifier: Programming Language :: Python :: 3.12
Classifier: Programming Language :: Python :: 3.13
Classifier: Programming Language :: Python :: 3.14
Classifier: Topic :: Security
Classifier: Typing :: Typed
Provides-Extra: all
Provides-Extra: db
Provides-Extra: fastapi
Requires-Dist: fastapi (>=0.100) ; extra == "fastapi" or extra == "all"
Requires-Dist: sqlalchemy (>=2.0,<3.0) ; extra == "db" or extra == "all"
Project-URL: Repository, https://github.com/insmnia/binauth
